{
  "bot_name": "quant-spot-live",
  "dry_run": false,
  "max_open_trades": 3,
  "stake_currency": "USDT",
  "stake_amount": 8,
  "tradable_balance_ratio": 0.5,
  "timeframe": "1h",
  "cancel_open_orders_on_exit": true,
  "trading_mode": "spot",
  "margin_mode": "",
  "db_url": "sqlite:////freqtrade/user_data/tradesv3.live.sqlite",
  "unfilledtimeout": {
    "entry": 10,
    "exit": 10,
    "exit_timeout_count": 0,
    "unit": "minutes"
  },
  "entry_pricing": {
    "price_side": "same",
    "use_order_book": true,
    "order_book_top": 1,
    "price_last_balance": 0.0,
    "check_depth_of_market": {
      "enabled": false,
      "bids_to_ask_delta": 1
    }
  },
  "exit_pricing": {
    "price_side": "same",
    "use_order_book": true,
    "order_book_top": 1
  },
  "exchange": {
    "name": "binance",
    "key": "",
    "secret": "",
    "enable_ws": false,
    "ccxt_config": {
      "enableRateLimit": true
    },
    "ccxt_async_config": {
      "enableRateLimit": true,
      "rateLimit": 200
    },
    "pair_whitelist": [
      "BTC/USDT",
      "ETH/USDT",
      "SOL/USDT",
      "XRP/USDT",
      "BNB/USDT",
      "DOGE/USDT",
      "ADA/USDT",
      "AVAX/USDT",
      "LINK/USDT",
      "DOT/USDT",
      "MATIC/USDT",
      "PEPE/USDT",
      "SHIB/USDT",
      "WIF/USDT",
      "ORDI/USDT",
      "BONK/USDT"
    ],
    "pair_blacklist": []
  },
  "order_types": {
    "entry": "limit",
    "exit": "limit",
    "emergency_exit": "market",
    "stoploss": "limit",
    "stoploss_on_exchange": false
  },
  "order_time_in_force": {
    "entry": "IOC",
    "exit": "IOC"
  },
  "pairlists": [
    {
      "method": "StaticPairList"
    }
  ],
  "api_server": {
    "enabled": true,
    "listen_ip_address": "0.0.0.0",
    "listen_port": 9013,
    "verbosity": "error",
    "enable_openapi": false,
    "CORS_origins": []
  },
  "initial_state": "running",
  "force_entry_enable": true,
  "internals": {
    "process_throttle_secs": 5
  }
}
